danmaku_tools/__init__.py
danmaku_tools/analyze_danmaku.py
danmaku_tools/clean_danmaku.py
danmaku_tools/cut_danmaku.py
danmaku_tools/danmaku_energy_map.py
danmaku_tools/danmaku_tools.py
danmaku_tools/he_video.py
danmaku_tools/merge_danmaku.py
danmaku_tools-0.0.9.dist-info/LICENSE
danmaku_tools-0.0.9.dist-info/METADATA
danmaku_tools-0.0.9.dist-info/WHEEL
danmaku_tools-0.0.9.dist-info/top_level.txt
danmaku_tools-0.0.9.dist-info/RECORD
