Metadata-Version: 2.1
Name: danmaku-tools
Version: 0.0.9
Summary: Process XML Danmaku File from BililiveRecorder
Home-page: https://github.com/valkjsaaa/danmaku_tools
Author: Jackie Yang
Author-email: jackie@jackieyang.me
Project-URL: Bug Tracker, https://github.com/valkjsaaa/danmaku_tools/issues
Classifier: Development Status :: 3 - Alpha
Classifier: Programming Language :: Python :: 3
Classifier: License :: OSI Approved :: GNU General Public License v3 (GPLv3)
Classifier: Operating System :: OS Independent
Requires-Python: >=3.7
License-File: LICENSE
Requires-Dist: matplotlib
Requires-Dist: numpy
Requires-Dist: scipy
Requires-Dist: python-dateutil
Requires-Dist: srt
Requires-Dist: tqdm
Requires-Dist: textrank4zh
